LICENSE
README.md
setup.py
flmedbenchmark.egg-info/PKG-INFO
flmedbenchmark.egg-info/SOURCES.txt
flmedbenchmark.egg-info/dependency_links.txt
flmedbenchmark.egg-info/requires.txt
flmedbenchmark.egg-info/top_level.txt
src/__init__.py
src/__main__.py
src/datasets/__init__.py
src/datasets/dataset.py
src/datasets/fate.py
src/datasets/flbdatasets.py
src/datasets/leaf.py
src/datasets/utils.py
src/logging/__init__.py
src/logging/common.py
src/logging/logger.py
src/logging/report.py