Metadata-Version: 2.1
Name: flmedbenchmark
Version: 0.1.0
Summary: flmedbenchmark
Home-page: https://https://github.com/Bye-legumes/FLMedbenchmark-toolkit-for-image
Author: zhilong
Author-email: zhilong.chen@mail.mcgill.ca
Requires-Python: >=3.6
License-File: LICENSE
